parkproxies/__init__.py
parkproxies/proxy.py
parkproxies/proxy_list.py
parkproxies/proxy_service.py
parkproxies-0.0.2.dist-info/METADATA
parkproxies-0.0.2.dist-info/WHEEL
parkproxies-0.0.2.dist-info/licenses/LICENSE
parkproxies-0.0.2.dist-info/RECORD
