Metadata-Version: 2.1
Name: parkproxies
Version: 0.0.2
Summary: Basic, free proxy utility.
Author-email: Parker G <parkerg34@gmail.com>
License-File: LICENSE
Classifier: License :: OSI Approved :: MIT License
Classifier: Operating System :: OS Independent
Classifier: Programming Language :: Python :: 3
Requires-Python: >=3.10
